funcy_chain/__init__.py
funcy_chain/chain.py
funcy_chain/chain_base.py
funcy_chain/iterchain.py
funcy_chain/utils.py
funcy_chain-0.3.1.dist-info/LICENSE
funcy_chain-0.3.1.dist-info/WHEEL
funcy_chain-0.3.1.dist-info/METADATA
funcy_chain-0.3.1.dist-info/RECORD
