Metadata-Version: 2.3
Name: funcy-chain
Version: 0.3.1
Summary: Method chaining with funcy.
Keywords: chain,method,chaining,funcy,method-chaining
Author-email: Tal Einat <taleinat@gmail.com>
Requires-Python: >=3.8
Classifier: License :: OSI Approved :: MIT License
Classifier: Programming Language :: Python :: 3
Classifier: Programming Language :: Python :: 3.8
Classifier: Programming Language :: Python :: 3.9
Classifier: Programming Language :: Python :: 3.10
Classifier: Programming Language :: Python :: 3.11
Classifier: Programming Language :: Python :: 3.12
Classifier: Programming Language :: Python :: 3.13
Classifier: Programming Language :: Python :: Implementation :: CPython
Requires-Dist: funcy >= 1.14
Requires-Dist: flit >=3.3, <4 ; extra == "dev"
Requires-Dist: black ; extra == "lint"
Requires-Dist: isort ; extra == "lint"
Requires-Dist: pylint ; extra == "lint"
Requires-Dist: pytest >= 2.7.3 ; extra == "test"
Requires-Dist: tox >=4.25.0, <5 ; extra == "test"
Project-URL: homepage, https://github.com/taleinat/funcy-chain
Project-URL: source, https://github.com/taleinat/funcy-chain.git
Provides-Extra: dev
Provides-Extra: lint
Provides-Extra: test
